odoo/addons/shopinvader_search_engine_product_brand_image/README.rst
odoo/addons/shopinvader_search_engine_product_brand_image/__init__.py
odoo/addons/shopinvader_search_engine_product_brand_image/__manifest__.py
odoo/addons/shopinvader_search_engine_product_brand_image/i18n/shopinvader_product_brand.pot
odoo/addons/shopinvader_search_engine_product_brand_image/i18n/shopinvader_product_brand_image.pot
odoo/addons/shopinvader_search_engine_product_brand_image/i18n/shopinvader_search_engine_product_brand_image.pot
odoo/addons/shopinvader_search_engine_product_brand_image/readme/CONTRIBUTORS.rst
odoo/addons/shopinvader_search_engine_product_brand_image/readme/DESCRIPTION.rst
odoo/addons/shopinvader_search_engine_product_brand_image/schemas/__init__.py
odoo/addons/shopinvader_search_engine_product_brand_image/schemas/brand.py
odoo/addons/shopinvader_search_engine_product_brand_image/static/description/index.html
odoo/addons/shopinvader_search_engine_product_brand_image/tests/__init__.py
odoo/addons/shopinvader_search_engine_product_brand_image/tests/common.py
odoo/addons/shopinvader_search_engine_product_brand_image/tests/test_brand.py
odoo_addon_shopinvader_search_engine_product_brand_image-16.0.1.0.0.4.dist-info/METADATA
odoo_addon_shopinvader_search_engine_product_brand_image-16.0.1.0.0.4.dist-info/WHEEL
odoo_addon_shopinvader_search_engine_product_brand_image-16.0.1.0.0.4.dist-info/top_level.txt
odoo_addon_shopinvader_search_engine_product_brand_image-16.0.1.0.0.4.dist-info/RECORD
